{
  "auth": {
    "awesomeproject69358958": {
      "customAuth": false,
      "dependsOn": [],
      "frontendAuthConfig": {
        "mfaConfiguration": "OFF",
        "mfaTypes": [
          "SMS"
        ],
        "passwordProtectionSettings": {
          "passwordPolicyCharacters": [],
          "passwordPolicyMinLength": 8
        },
        "signupAttributes": [
          "EMAIL"
        ],
        "socialProviders": [],
        "usernameAttributes": [],
        "verificationMechanisms": [
          "EMAIL"
        ]
      },
      "providerPlugin": "awscloudformation",
      "service": "Cognito"
    },
    "userPoolGroups": {
      "dependsOn": [
        {
          "attributes": [
            "UserPoolId",
            "AppClientIDWeb",
            "AppClientID"
          ],
          "category": "auth",
          "resourceName": "awesomeproject69358958"
        }
      ],
      "providerPlugin": "awscloudformation",
      "service": "Cognito-UserPool-Groups"
    }
  }
}